hotglue_singer_sdk/__init__.py
hotglue_singer_sdk/authenticators.py
hotglue_singer_sdk/cli/__init__.py
hotglue_singer_sdk/cli/common_options.py
hotglue_singer_sdk/configuration/__init__.py
hotglue_singer_sdk/configuration/_dict_config.py
hotglue_singer_sdk/exceptions.py
hotglue_singer_sdk/helpers/__init__.py
hotglue_singer_sdk/helpers/_catalog.py
hotglue_singer_sdk/helpers/_classproperty.py
hotglue_singer_sdk/helpers/_compat.py
hotglue_singer_sdk/helpers/_flattening.py
hotglue_singer_sdk/helpers/_schema.py
hotglue_singer_sdk/helpers/_secrets.py
hotglue_singer_sdk/helpers/_simpleeval.py
hotglue_singer_sdk/helpers/_singer.py
hotglue_singer_sdk/helpers/_state.py
hotglue_singer_sdk/helpers/_typing.py
hotglue_singer_sdk/helpers/_util.py
hotglue_singer_sdk/helpers/capabilities.py
hotglue_singer_sdk/helpers/jsonpath.py
hotglue_singer_sdk/io_base.py
hotglue_singer_sdk/mapper.py
hotglue_singer_sdk/mapper_base.py
hotglue_singer_sdk/plugin_base.py
hotglue_singer_sdk/py.typed
hotglue_singer_sdk/sinks/__init__.py
hotglue_singer_sdk/sinks/batch.py
hotglue_singer_sdk/sinks/core.py
hotglue_singer_sdk/sinks/record.py
hotglue_singer_sdk/sinks/sql.py
hotglue_singer_sdk/streams/__init__.py
hotglue_singer_sdk/streams/core.py
hotglue_singer_sdk/streams/graphql.py
hotglue_singer_sdk/streams/rest.py
hotglue_singer_sdk/streams/sql.py
hotglue_singer_sdk/tap_base.py
hotglue_singer_sdk/target_base.py
hotglue_singer_sdk/target_sdk/__init__.py
hotglue_singer_sdk/target_sdk/auth.py
hotglue_singer_sdk/target_sdk/client.py
hotglue_singer_sdk/target_sdk/common.py
hotglue_singer_sdk/target_sdk/lambda.py
hotglue_singer_sdk/target_sdk/rest.py
hotglue_singer_sdk/target_sdk/sinks.py
hotglue_singer_sdk/target_sdk/target.py
hotglue_singer_sdk/target_sdk/target_base.py
hotglue_singer_sdk/testing.py
hotglue_singer_sdk/typing.py
hotglue_singer_sdk-1.0.3.dist-info/METADATA
hotglue_singer_sdk-1.0.3.dist-info/WHEEL
hotglue_singer_sdk-1.0.3.dist-info/licenses/LICENSE
hotglue_singer_sdk-1.0.3.dist-info/RECORD
